{"stem":"049","instances":[{"docId":"entry__1914-10-14","docUri":"entry__1914-10-14.html","score":1,"contexts":[{"form":"049","weight":"1","pos":39,"context":"....net\/21.11115\/0000-000C-<mark>049<\/mark>E-E Faksimile PDF TEI Zeige Register ","fid":"copyLinkTextfield"}]},{"docId":"entry__1914-10-10","docUri":"entry__1914-10-10.html","score":1,"contexts":[{"form":"049","weight":"1","pos":89,"context":"....net\/21.11115\/0000-000C-<mark>049<\/mark>A-2 Faksimile PDF TEI Zeige Register ","fid":"copyLinkTextfield"}]},{"docId":"entry__1900-03-21","docUri":"entry__1900-03-21.html","score":1,"contexts":[{"form":"049","weight":"1","pos":26,"context":"....net\/21.11115\/0000-000B-F<mark>049<\/mark>-4 Faksimile PDF TEI Zeige Register ","fid":"copyLinkTextfield"}]},{"docId":"entry__1914-10-11","docUri":"entry__1914-10-11.html","score":1,"contexts":[{"form":"049","weight":"1","pos":84,"context":"....net\/21.11115\/0000-000C-<mark>049<\/mark>B-1 Faksimile PDF TEI Zeige Register ","fid":"copyLinkTextfield"}]},{"docId":"entry__1914-10-13","docUri":"entry__1914-10-13.html","score":1,"contexts":[{"form":"049","weight":"1","pos":77,"context":"....net\/21.11115\/0000-000C-<mark>049<\/mark>D-F Faksimile PDF TEI Zeige Register ","fid":"copyLinkTextfield"}]},{"docId":"entry__1914-10-15","docUri":"entry__1914-10-15.html","score":1,"contexts":[{"form":"049","weight":"1","pos":43,"context":"....net\/21.11115\/0000-000C-<mark>049<\/mark>F-D Faksimile PDF TEI Zeige Register ","fid":"copyLinkTextfield"}]},{"docId":"entry__1888-05-29","docUri":"entry__1888-05-29.html","score":1,"contexts":[{"form":"049","weight":"1","pos":30,"context":"....net\/21.11115\/0000-000B-E<mark>049<\/mark>-6 Faksimile PDF TEI Zeige Register ","fid":"copyLinkTextfield"}]},{"docId":"entry__1914-10-12","docUri":"entry__1914-10-12.html","score":1,"contexts":[{"form":"049","weight":"1","pos":35,"context":"....net\/21.11115\/0000-000C-<mark>049<\/mark>C-0 Faksimile PDF TEI Zeige Register ","fid":"copyLinkTextfield"}]}]}