{"stem":"071","instances":[{"docId":"entry__1888-07-08","docUri":"entry__1888-07-08.html","score":1,"contexts":[{"form":"071","weight":"1","pos":27,"context":"....net\/21.11115\/0000-000B-E<mark>071<\/mark>-8 Faksimile PDF TEI Zeige Register ","fid":"copyLinkTextfield"}]},{"docId":"entry__1900-04-30","docUri":"entry__1900-04-30.html","score":1,"contexts":[{"form":"071","weight":"1","pos":25,"context":"....net\/21.11115\/0000-000B-F<mark>071<\/mark>-6 Faksimile PDF TEI Zeige Register ","fid":"copyLinkTextfield"}]},{"docId":"entry__1916-07-14","docUri":"entry__1916-07-14.html","score":1,"contexts":[{"form":"071","weight":"1","pos":56,"context":"....net\/21.11115\/0000-000C-<mark>071<\/mark>C-E Faksimile PDF TEI Zeige Register ","fid":"copyLinkTextfield"}]},{"docId":"entry__1916-07-12","docUri":"entry__1916-07-12.html","score":1,"contexts":[{"form":"071","weight":"1","pos":65,"context":"....net\/21.11115\/0000-000C-<mark>071<\/mark>A-0 Faksimile PDF TEI Zeige Register ","fid":"copyLinkTextfield"}]},{"docId":"entry__1916-07-17","docUri":"entry__1916-07-17.html","score":1,"contexts":[{"form":"071","weight":"1","pos":35,"context":"....net\/21.11115\/0000-000C-<mark>071<\/mark>F-B Faksimile PDF TEI Zeige Register ","fid":"copyLinkTextfield"}]},{"docId":"entry__1916-07-13","docUri":"entry__1916-07-13.html","score":1,"contexts":[{"form":"071","weight":"1","pos":63,"context":"....net\/21.11115\/0000-000C-<mark>071<\/mark>B-F Faksimile PDF TEI Zeige Register ","fid":"copyLinkTextfield"}]},{"docId":"entry__1916-07-15","docUri":"entry__1916-07-15.html","score":1,"contexts":[{"form":"071","weight":"1","pos":33,"context":"....net\/21.11115\/0000-000C-<mark>071<\/mark>D-D Faksimile PDF TEI Zeige Register ","fid":"copyLinkTextfield"}]},{"docId":"entry__1916-07-16","docUri":"entry__1916-07-16.html","score":1,"contexts":[{"form":"071","weight":"1","pos":44,"context":"....net\/21.11115\/0000-000C-<mark>071<\/mark>E-C Faksimile PDF TEI Zeige Register ","fid":"copyLinkTextfield"}]}]}