{"stem":"093","instances":[{"docId":"entry__1900-06-03","docUri":"entry__1900-06-03.html","score":1,"contexts":[{"form":"093","weight":"1","pos":27,"context":"....net\/21.11115\/0000-000B-F<mark>093<\/mark>-F Faksimile PDF TEI Zeige Register ","fid":"copyLinkTextfield"}]},{"docId":"entry__1918-01-13","docUri":"entry__1918-01-13.html","score":1,"contexts":[{"form":"093","weight":"1","pos":75,"context":"....net\/21.11115\/0000-000C-<mark>093<\/mark>F-5 Faksimile PDF TEI Zeige Register ","fid":"copyLinkTextfield"}]},{"docId":"entry__1918-01-12","docUri":"entry__1918-01-12.html","score":1,"contexts":[{"form":"093","weight":"1","pos":85,"context":"....net\/21.11115\/0000-000C-<mark>093<\/mark>E-6 Faksimile PDF TEI Zeige Register ","fid":"copyLinkTextfield"}]},{"docId":"entry__1888-08-11","docUri":"entry__1888-08-11.html","score":1,"contexts":[{"form":"093","weight":"1","pos":24,"context":"....net\/21.11115\/0000-000B-E<mark>093<\/mark>-1 Faksimile PDF TEI Zeige Register ","fid":"copyLinkTextfield"}]},{"docId":"entry__1918-01-11","docUri":"entry__1918-01-11.html","score":1,"contexts":[{"form":"093","weight":"1","pos":97,"context":"....net\/21.11115\/0000-000C-<mark>093<\/mark>D-7 Faksimile PDF TEI Zeige Register ","fid":"copyLinkTextfield"}]},{"docId":"entry__1918-01-10","docUri":"entry__1918-01-10.html","score":1,"contexts":[{"form":"093","weight":"1","pos":80,"context":"....net\/21.11115\/0000-000C-<mark>093<\/mark>C-8 Faksimile PDF TEI Zeige Register ","fid":"copyLinkTextfield"}]},{"docId":"entry__1918-01-08","docUri":"entry__1918-01-08.html","score":1,"contexts":[{"form":"093","weight":"1","pos":127,"context":"....net\/21.11115\/0000-000C-<mark>093<\/mark>A-A Faksimile PDF TEI Zeige Register ","fid":"copyLinkTextfield"}]},{"docId":"entry__1918-01-09","docUri":"entry__1918-01-09.html","score":1,"contexts":[{"form":"093","weight":"1","pos":60,"context":"....net\/21.11115\/0000-000C-<mark>093<\/mark>B-9 Faksimile PDF TEI Zeige Register ","fid":"copyLinkTextfield"}]}]}