{"stem":"351","instances":[{"docId":"entry__1902-07-11","docUri":"entry__1902-07-11.html","score":1,"contexts":[{"form":"351","weight":"1","pos":29,"context":"....net\/21.11115\/0000-000B-F<mark>351<\/mark>-7 Faksimile PDF TEI Zeige Register ","fid":"copyLinkTextfield"}]},{"docId":"entry__1890-10-31","docUri":"entry__1890-10-31.html","score":1,"contexts":[{"form":"351","weight":"1","pos":33,"context":"....net\/21.11115\/0000-000B-E<mark>351<\/mark>-9 Faksimile PDF TEI Zeige Register ","fid":"copyLinkTextfield"}]},{"docId":"entry__1905-12-21","docUri":"entry__1905-12-21.html","score":1,"contexts":[{"form":"351","weight":"1","pos":80,"context":"Streichquartett Nr. 11 E-Dur op. 125,2 D <mark>351<\/mark>","fid":"nav-contact"}]},{"docId":"entry__1912-08-31","docUri":"entry__1912-08-31.html","score":1,"contexts":[{"form":"351","weight":"1","pos":22,"context":"   1912: VIII 31 ― IX 5 <mark>351<\/mark>    ","fid":"div__26"}]},{"docId":"entry__1891-10-02","docUri":"entry__1891-10-02.html","score":1,"contexts":[{"form":"351","weight":"1","pos":21,"context":"...Die erleuchteten 1891: X 2 - X 9 <mark>351<\/mark> Straßen.― (Kaisers Ankunft.)","fid":"p__6"}]},{"docId":"entry__1901-04-23","docUri":"entry__1901-04-23.html","score":1,"contexts":[{"form":"351","weight":"1","pos":14,"context":"  1901: IV 24 - V 3 <mark>351<\/mark> ","fid":"div__11"}]}]}