{"stem":"aba","instances":[{"docId":"entry__1919-01-27","docUri":"entry__1919-01-27.html","score":1,"contexts":[{"form":"ABA","weight":"1","pos":31,"context":"....net\/21.11115\/0000-000C-0<mark>ABA<\/mark>-8 Faksimile PDF TEI Zeige Register ","fid":"copyLinkTextfield"}]},{"docId":"entry__1930-04-18","docUri":"entry__1930-04-18.html","score":1,"contexts":[{"form":"ABA","weight":"1","pos":31,"context":"....net\/21.11115\/0000-000C-1<mark>ABA<\/mark>-6 Faksimile PDF TEI Zeige Register ","fid":"copyLinkTextfield"}]}]}