{"stem":"ac-","instances":[{"docId":"entry__1924-08-24","docUri":"entry__1924-08-24.html","score":1,"contexts":[{"form":"AC-E","weight":"1","pos":86,"context":"....net\/21.11115\/0000-000C-12<mark>AC-E<\/mark> Faksimile PDF TEI Zeige Register ","fid":"copyLinkTextfield"}]},{"docId":"entry__1914-10-28","docUri":"entry__1914-10-28.html","score":1,"contexts":[{"form":"AC-E","weight":"1","pos":42,"context":"....net\/21.11115\/0000-000C-04<mark>AC-E<\/mark> Faksimile PDF TEI Zeige Register ","fid":"copyLinkTextfield"}]},{"docId":"entry__1904-11-27","docUri":"entry__1904-11-27.html","score":1,"contexts":[{"form":"AC-E","weight":"1","pos":36,"context":"...net\/21.11115\/0000-000B-F6<mark>AC-E<\/mark> Faksimile PDF TEI Zeige Register ","fid":"copyLinkTextfield"}]},{"docId":"entry__1894-09-20","docUri":"entry__1894-09-20.html","score":1,"contexts":[{"form":"AC-E","weight":"1","pos":64,"context":"...net\/21.11115\/0000-000B-E8<mark>AC-E<\/mark> Faksimile PDF TEI Zeige Register ","fid":"copyLinkTextfield"}]}]}