{"stem":"anthoni","instances":[{"docId":"entry__1926-02-12","docUri":"entry__1926-02-12.html","score":1,"contexts":[{"form":"Anthonis","weight":"1","pos":117,"context":" Dyck <mark>Anthonis<\/mark> van ","fid":"nav-profile"}]},{"docId":"entry__1924-07-04","docUri":"entry__1924-07-04.html","score":1,"contexts":[{"form":"Anthony","weight":"1","pos":107,"context":" Marcus Joseph <mark>Anthony<\/mark> ","fid":"nav-profile"}]},{"docId":"entry__1913-07-01","docUri":"entry__1913-07-01.html","score":1,"contexts":[{"form":"Anthonis","weight":"1","pos":138,"context":" Dyck <mark>Anthonis<\/mark> van ","fid":"nav-profile"}]}]}