{"stem":"bakchantinnen","instances":[{"docId":"entry__1931-06-29","docUri":"entry__1931-06-29.html","score":1,"contexts":[{"form":"Bakchantinnen","weight":"1","pos":136,"context":"Die <mark>Bakchantinnen<\/mark>","fid":"nav-contact"}]},{"docId":"entry__1931-07-04","docUri":"entry__1931-07-04.html","score":1,"contexts":[{"form":"Bakchantinnen","weight":"1","pos":128,"context":"Die <mark>Bakchantinnen<\/mark>","fid":"nav-contact"}]},{"docId":"entry__1930-10-28","docUri":"entry__1930-10-28.html","score":1,"contexts":[{"form":"Bakchantinnen","weight":"1","pos":139,"context":"Die <mark>Bakchantinnen<\/mark>","fid":"nav-contact"}]}]}