{"stem":"baláz","instances":[{"docId":"entry__1926-11-21","docUri":"entry__1926-11-21.html","score":2,"contexts":[{"form":"Balázs","weight":"1","pos":136,"context":"...Werbezirk, Moser). Sprach viele noch flüchtig: <mark>Balázs<\/mark> (jetzt Berlin), Lvovsky, Erika Wagner, die...","fid":"p__37"},{"form":"Balázs","weight":"1","pos":159,"context":" <mark>Balázs<\/mark> Béla ","fid":"nav-profile"}]},{"docId":"entry__1929-04-28","docUri":"entry__1929-04-28.html","score":1,"contexts":[{"form":"Balázs","weight":"1","pos":46,"context":" <mark>Balázs<\/mark> Béla ","fid":"nav-profile"}]},{"docId":"entry__1929-03-16","docUri":"entry__1929-03-16.html","score":1,"contexts":[{"form":"Balázs","weight":"1","pos":54,"context":" <mark>Balázs<\/mark> Béla ","fid":"nav-profile"}]},{"docId":"entry__1929-05-20","docUri":"entry__1929-05-20.html","score":1,"contexts":[{"form":"Balázs","weight":"1","pos":44,"context":" <mark>Balázs<\/mark> Béla ","fid":"nav-profile"}]},{"docId":"entry__1929-03-31","docUri":"entry__1929-03-31.html","score":1,"contexts":[{"form":"Balázs","weight":"1","pos":51,"context":" <mark>Balázs<\/mark> Béla ","fid":"nav-profile"}]},{"docId":"entry__1926-05-27","docUri":"entry__1926-05-27.html","score":1,"contexts":[{"form":"Balázs","weight":"1","pos":48,"context":" <mark>Balázs<\/mark> Béla ","fid":"nav-profile"}]},{"docId":"entry__1929-05-19","docUri":"entry__1929-05-19.html","score":1,"contexts":[{"form":"Balázs","weight":"1","pos":40,"context":" <mark>Balázs<\/mark> Béla ","fid":"nav-profile"}]}]}