{"stem":"chudzikiewicz","instances":[{"docId":"entry__1900-12-09","docUri":"entry__1900-12-09.html","score":1,"contexts":[{"form":"Chudzikiewicz","weight":"1","pos":36,"context":" <mark>Chudzikiewicz<\/mark> Helene ","fid":"nav-profile"}]},{"docId":"entry__1900-06-11","docUri":"entry__1900-06-11.html","score":1,"contexts":[{"form":"Chudzikiewicz","weight":"1","pos":62,"context":" <mark>Chudzikiewicz<\/mark> Helene ","fid":"nav-profile"}]},{"docId":"entry__1900-06-07","docUri":"entry__1900-06-07.html","score":1,"contexts":[{"form":"Chudzikiewicz","weight":"1","pos":46,"context":" <mark>Chudzikiewicz<\/mark> Helene ","fid":"nav-profile"}]},{"docId":"entry__1900-05-22","docUri":"entry__1900-05-22.html","score":1,"contexts":[{"form":"Chudzikiewicz","weight":"1","pos":50,"context":" <mark>Chudzikiewicz<\/mark> Helene ","fid":"nav-profile"}]},{"docId":"entry__1900-06-26","docUri":"entry__1900-06-26.html","score":1,"contexts":[{"form":"Chudzikiewicz","weight":"1","pos":43,"context":" <mark>Chudzikiewicz<\/mark> Helene ","fid":"nav-profile"}]}]}