{"stem":"cornelius","instances":[{"docId":"entry__1880-03-29","docUri":"entry__1880-03-29.html","score":2,"contexts":[{"form":"Cornelius","weight":"1","pos":59,"context":"<mark>Cornelius<\/mark> Ombra (zur selben Zeit) ein Trauerspiel in 2 Theilen...","fid":"p__8"},{"form":"Cornelius","weight":"1","pos":124,"context":"<mark>Cornelius<\/mark> Ombra","fid":"nav-contact"}]},{"docId":"entry__1891-06-04","docUri":"entry__1891-06-04.html","score":2,"contexts":[{"form":"Cornelius","weight":"1","pos":12,"context":"Vorgestern war ihre Antrittsrolle, in <mark>Cornelius<\/mark> Voss; sie hat gefallen. Morgen spielt sie...","fid":"p__4"},{"form":"Cornelius","weight":"1","pos":67,"context":"<mark>Cornelius<\/mark> Voss","fid":"nav-contact"}]},{"docId":"entry__1905-12-04","docUri":"entry__1905-12-04.html","score":2,"contexts":[{"form":"Cornelius","weight":"1","pos":48,"context":"Abends Grethe Samuely da.― Lieder von Wolf, <mark>Cornelius<\/mark> etc. durchgespielt.―","fid":"p__8"},{"form":"Cornelius","weight":"1","pos":84,"context":" <mark>Cornelius<\/mark> Peter ","fid":"nav-profile"}]},{"docId":"entry__1880-05-24","docUri":"entry__1880-05-24.html","score":2,"contexts":[{"form":"Cornelius","weight":"1","pos":119,"context":"<mark>Cornelius<\/mark> Ombra Juni 74 (2 Akte?)","fid":"p__21"},{"form":"Cornelius","weight":"1","pos":216,"context":"<mark>Cornelius<\/mark> Ombra","fid":"nav-contact"}]},{"docId":"entry__1918-03-10","docUri":"entry__1918-03-10.html","score":2,"contexts":[{"form":"Cornelius","weight":"1","pos":40,"context":"...;― Fleischer mit Frau, der, von Gund begleitet <mark>Cornelius<\/mark>, Loewe und Brahms sehr talentvoll aber nicht sehr...","fid":"p__19"},{"form":"Cornelius","weight":"1","pos":78,"context":" <mark>Cornelius<\/mark> Peter ","fid":"nav-profile"}]},{"docId":"entry__1928-06-05","docUri":"entry__1928-06-05.html","score":2,"contexts":[{"form":"Cornelius","weight":"1","pos":33,"context":"Mit C. P. Oper Strawinskys Oedipus;― <mark>Cornelius<\/mark> Barbier von Bagdad.―","fid":"p__11"},{"form":"Cornelius","weight":"1","pos":73,"context":" <mark>Cornelius<\/mark> Peter ","fid":"nav-profile"}]},{"docId":"entry__1922-05-03","docUri":"entry__1922-05-03.html","score":1,"contexts":[{"form":"Cornelius","weight":"1","pos":95,"context":" Rossem <mark>Cornelius<\/mark> Petrus van ","fid":"nav-profile"}]},{"docId":"entry__1920-12-26","docUri":"entry__1920-12-26.html","score":1,"contexts":[{"form":"Cornelius","weight":"1","pos":106,"context":" Kirschner <mark>Cornelius<\/mark> ","fid":"nav-profile"}]},{"docId":"entry__1888-11-09","docUri":"entry__1888-11-09.html","score":1,"contexts":[{"form":"Cornelius","weight":"1","pos":43,"context":"<mark>Cornelius<\/mark> Voss","fid":"nav-contact"}]}]}