{"stem":"e-c","instances":[{"docId":"entry__1899-08-13","docUri":"entry__1899-08-13.html","score":1,"contexts":[{"form":"E-C","weight":"1","pos":26,"context":"...net\/21.11115\/0000-000B-EF7<mark>E-C<\/mark> Faksimile PDF TEI Zeige Register ","fid":"copyLinkTextfield"}]},{"docId":"entry__1897-10-30","docUri":"entry__1897-10-30.html","score":1,"contexts":[{"form":"E-C","weight":"1","pos":42,"context":"...net\/21.11115\/0000-000B-ED0<mark>E-C<\/mark> Faksimile PDF TEI Zeige Register ","fid":"copyLinkTextfield"}]},{"docId":"entry__1926-01-04","docUri":"entry__1926-01-04.html","score":1,"contexts":[{"form":"E-C","weight":"1","pos":57,"context":"...net\/21.11115\/0000-000C-149<mark>E-C<\/mark> Faksimile PDF TEI Zeige Register ","fid":"copyLinkTextfield"}]},{"docId":"entry__1902-07-08","docUri":"entry__1902-07-08.html","score":1,"contexts":[{"form":"E-C","weight":"1","pos":27,"context":"...net\/21.11115\/0000-000B-F34<mark>E-C<\/mark> Faksimile PDF TEI Zeige Register ","fid":"copyLinkTextfield"}]},{"docId":"entry__1926-05-12","docUri":"entry__1926-05-12.html","score":1,"contexts":[{"form":"E-C","weight":"1","pos":59,"context":"...net\/21.11115\/0000-000C-151<mark>E-C<\/mark> Faksimile PDF TEI Zeige Register ","fid":"copyLinkTextfield"}]},{"docId":"entry__1913-10-26","docUri":"entry__1913-10-26.html","score":1,"contexts":[{"form":"E-C","weight":"1","pos":58,"context":"...net\/21.11115\/0000-000C-033<mark>E-C<\/mark> Faksimile PDF TEI Zeige Register ","fid":"copyLinkTextfield"}]},{"docId":"entry__1919-08-12","docUri":"entry__1919-08-12.html","score":1,"contexts":[{"form":"E-C","weight":"1","pos":74,"context":"....net\/21.11115\/0000-000C-0B7<mark>E-C<\/mark> Faksimile PDF TEI Zeige Register ","fid":"copyLinkTextfield"}]},{"docId":"entry__1879-11-01","docUri":"entry__1879-11-01.html","score":1,"contexts":[{"form":"E-C","weight":"1","pos":36,"context":"...net\/21.11115\/0000-000B-DD1<mark>E-C<\/mark> Faksimile PDF TEI Zeige Register ","fid":"copyLinkTextfield"}]},{"docId":"entry__1890-11-13","docUri":"entry__1890-11-13.html","score":1,"contexts":[{"form":"E-C","weight":"1","pos":25,"context":"...net\/21.11115\/0000-000B-E35<mark>E-C<\/mark> Faksimile PDF TEI Zeige Register ","fid":"copyLinkTextfield"}]},{"docId":"entry__1901-01-03","docUri":"entry__1901-01-03.html","score":1,"contexts":[{"form":"E-C","weight":"1","pos":40,"context":"...net\/21.11115\/0000-000B-F15<mark>E-C<\/mark> Faksimile PDF TEI Zeige Register ","fid":"copyLinkTextfield"}]},{"docId":"entry__1896-02-03","docUri":"entry__1896-02-03.html","score":1,"contexts":[{"form":"E-C","weight":"1","pos":35,"context":"...net\/21.11115\/0000-000B-EA9<mark>E-C<\/mark> Faksimile PDF TEI Zeige Register ","fid":"copyLinkTextfield"}]},{"docId":"entry__1912-06-17","docUri":"entry__1912-06-17.html","score":1,"contexts":[{"form":"E-C","weight":"1","pos":36,"context":"...net\/21.11115\/0000-000C-014<mark>E-C<\/mark> Faksimile PDF TEI Zeige Register ","fid":"copyLinkTextfield"}]},{"docId":"entry__1897-06-23","docUri":"entry__1897-06-23.html","score":1,"contexts":[{"form":"E-C","weight":"1","pos":34,"context":"...net\/21.11115\/0000-000B-EC8<mark>E-C<\/mark> Faksimile PDF TEI Zeige Register ","fid":"copyLinkTextfield"}]},{"docId":"entry__1929-06-06","docUri":"entry__1929-06-06.html","score":1,"contexts":[{"form":"E-C","weight":"1","pos":45,"context":"...net\/21.11115\/0000-000C-197<mark>E-C<\/mark> Faksimile PDF TEI Zeige Register ","fid":"copyLinkTextfield"}]},{"docId":"entry__1925-01-01","docUri":"entry__1925-01-01.html","score":1,"contexts":[{"form":"E-C","weight":"1","pos":71,"context":"...net\/21.11115\/0000-000C-132<mark>E-C<\/mark> Faksimile PDF TEI Zeige Register ","fid":"copyLinkTextfield"}]},{"docId":"entry__1906-08-16","docUri":"entry__1906-08-16.html","score":1,"contexts":[{"form":"E-C","weight":"1","pos":29,"context":"...net\/21.11115\/0000-000B-F91<mark>E-C<\/mark> Faksimile PDF TEI Zeige Register ","fid":"copyLinkTextfield"}]},{"docId":"entry__1927-09-21","docUri":"entry__1927-09-21.html","score":1,"contexts":[{"form":"E-C","weight":"1","pos":83,"context":"...net\/21.11115\/0000-000C-170<mark>E-C<\/mark> Faksimile PDF TEI Zeige Register ","fid":"copyLinkTextfield"}]},{"docId":"entry__1889-03-28","docUri":"entry__1889-03-28.html","score":1,"contexts":[{"form":"E-C","weight":"1","pos":456,"context":"...net\/21.11115\/0000-000B-E16<mark>E-C<\/mark> Faksimile PDF TEI Zeige Register ","fid":"copyLinkTextfield"}]},{"docId":"entry__1911-02-23","docUri":"entry__1911-02-23.html","score":1,"contexts":[{"form":"E-C","weight":"1","pos":100,"context":"...net\/21.11115\/0000-000B-FF6<mark>E-C<\/mark> Faksimile PDF TEI Zeige Register ","fid":"copyLinkTextfield"}]},{"docId":"entry__1917-07-19","docUri":"entry__1917-07-19.html","score":1,"contexts":[{"form":"E-C","weight":"1","pos":48,"context":"...net\/21.11115\/0000-000C-088<mark>E-C<\/mark> Faksimile PDF TEI Zeige Register ","fid":"copyLinkTextfield"}]},{"docId":"entry__1906-04-10","docUri":"entry__1906-04-10.html","score":1,"contexts":[{"form":"E-C","weight":"1","pos":69,"context":"...net\/21.11115\/0000-000B-F89<mark>E-C<\/mark> Faksimile PDF TEI Zeige Register ","fid":"copyLinkTextfield"}]},{"docId":"entry__1896-06-10","docUri":"entry__1896-06-10.html","score":1,"contexts":[{"form":"E-C","weight":"1","pos":37,"context":"...net\/21.11115\/0000-000B-EB1<mark>E-C<\/mark> Faksimile PDF TEI Zeige Register ","fid":"copyLinkTextfield"}]},{"docId":"entry__1923-08-23","docUri":"entry__1923-08-23.html","score":1,"contexts":[{"form":"E-C","weight":"1","pos":37,"context":"...net\/21.11115\/0000-000C-113<mark>E-C<\/mark> Faksimile PDF TEI Zeige Register ","fid":"copyLinkTextfield"}]},{"docId":"entry__1915-03-08","docUri":"entry__1915-03-08.html","score":1,"contexts":[{"form":"E-C","weight":"1","pos":31,"context":"...net\/21.11115\/0000-000C-052<mark>E-C<\/mark> Faksimile PDF TEI Zeige Register ","fid":"copyLinkTextfield"}]},{"docId":"entry__1903-11-27","docUri":"entry__1903-11-27.html","score":1,"contexts":[{"form":"E-C","weight":"1","pos":78,"context":"...net\/21.11115\/0000-000B-F53<mark>E-C<\/mark> Faksimile PDF TEI Zeige Register ","fid":"copyLinkTextfield"}]},{"docId":"entry__1917-11-25","docUri":"entry__1917-11-25.html","score":1,"contexts":[{"form":"E-C","weight":"1","pos":137,"context":"...net\/21.11115\/0000-000C-090<mark>E-C<\/mark> Faksimile PDF TEI Zeige Register ","fid":"copyLinkTextfield"}]},{"docId":"entry__1916-03-10","docUri":"entry__1916-03-10.html","score":1,"contexts":[{"form":"E-C","weight":"1","pos":114,"context":"...net\/21.11115\/0000-000C-069<mark>E-C<\/mark> Faksimile PDF TEI Zeige Register ","fid":"copyLinkTextfield"}]},{"docId":"entry__1905-04-07","docUri":"entry__1905-04-07.html","score":1,"contexts":[{"form":"E-C","weight":"1","pos":43,"context":"...net\/21.11115\/0000-000B-F72<mark>E-C<\/mark> Faksimile PDF TEI Zeige Register ","fid":"copyLinkTextfield"}]},{"docId":"entry__1909-10-15","docUri":"entry__1909-10-15.html","score":1,"contexts":[{"form":"E-C","weight":"1","pos":60,"context":"...net\/21.11115\/0000-000B-FD7<mark>E-C<\/mark> Faksimile PDF TEI Zeige Register ","fid":"copyLinkTextfield"}]},{"docId":"entry__1895-01-31","docUri":"entry__1895-01-31.html","score":1,"contexts":[{"form":"E-C","weight":"1","pos":123,"context":"...net\/21.11115\/0000-000B-E92<mark>E-C<\/mark> Faksimile PDF TEI Zeige Register ","fid":"copyLinkTextfield"}]},{"docId":"entry__1892-05-06","docUri":"entry__1892-05-06.html","score":1,"contexts":[{"form":"E-C","weight":"1","pos":26,"context":"...net\/21.11115\/0000-000B-E54<mark>E-C<\/mark> Faksimile PDF TEI Zeige Register ","fid":"copyLinkTextfield"}]},{"docId":"entry__1922-04-30","docUri":"entry__1922-04-30.html","score":1,"contexts":[{"form":"E-C","weight":"1","pos":47,"context":"....net\/21.11115\/0000-000C-0F5<mark>E-C<\/mark> Faksimile PDF TEI Zeige Register ","fid":"copyLinkTextfield"}]},{"docId":"entry__1927-05-16","docUri":"entry__1927-05-16.html","score":1,"contexts":[{"form":"E-C","weight":"1","pos":69,"context":"...net\/21.11115\/0000-000C-168<mark>E-C<\/mark> Faksimile PDF TEI Zeige Register ","fid":"copyLinkTextfield"}]},{"docId":"entry__1907-08-19","docUri":"entry__1907-08-19.html","score":1,"contexts":[{"form":"E-C","weight":"1","pos":32,"context":"...net\/21.11115\/0000-000B-FA8<mark>E-C<\/mark> Faksimile PDF TEI Zeige Register ","fid":"copyLinkTextfield"}]},{"docId":"entry__1883-01-06","docUri":"entry__1883-01-06.html","score":1,"contexts":[{"form":"E-C","weight":"1","pos":41,"context":"...net\/21.11115\/0000-000B-DE8<mark>E-C<\/mark> Faksimile PDF TEI Zeige Register ","fid":"copyLinkTextfield"}]},{"docId":"entry__1930-10-15","docUri":"entry__1930-10-15.html","score":1,"contexts":[{"form":"E-C","weight":"1","pos":78,"context":"....net\/21.11115\/0000-000C-1B6<mark>E-C<\/mark> Faksimile PDF TEI Zeige Register ","fid":"copyLinkTextfield"}]},{"docId":"entry__1920-12-20","docUri":"entry__1920-12-20.html","score":1,"contexts":[{"form":"E-C","weight":"1","pos":72,"context":"....net\/21.11115\/0000-000C-0D6<mark>E-C<\/mark> Faksimile PDF TEI Zeige Register ","fid":"copyLinkTextfield"}]},{"docId":"entry__1908-01-30","docUri":"entry__1908-01-30.html","score":1,"contexts":[{"form":"E-C","weight":"1","pos":67,"context":"...net\/21.11115\/0000-000B-FB0<mark>E-C<\/mark> Faksimile PDF TEI Zeige Register ","fid":"copyLinkTextfield"}]},{"docId":"entry__1885-12-12","docUri":"entry__1885-12-12.html","score":1,"contexts":[{"form":"E-C","weight":"1","pos":26,"context":"...net\/21.11115\/0000-000B-DF0<mark>E-C<\/mark> Faksimile PDF TEI Zeige Register ","fid":"copyLinkTextfield"}]},{"docId":"entry__1916-07-16","docUri":"entry__1916-07-16.html","score":1,"contexts":[{"form":"E-C","weight":"1","pos":45,"context":"...net\/21.11115\/0000-000C-071<mark>E-C<\/mark> Faksimile PDF TEI Zeige Register ","fid":"copyLinkTextfield"}]},{"docId":"entry__1893-09-17","docUri":"entry__1893-09-17.html","score":1,"contexts":[{"form":"E-C","weight":"1","pos":43,"context":"...net\/21.11115\/0000-000B-E73<mark>E-C<\/mark> Faksimile PDF TEI Zeige Register ","fid":"copyLinkTextfield"}]}]}