{"stem":"ffd","instances":[{"docId":"entry__1911-06-03","docUri":"entry__1911-06-03.html","score":1,"contexts":[{"form":"FFD","weight":"1","pos":38,"context":"....net\/21.11115\/0000-000B-<mark>FFD<\/mark>2-9 Faksimile PDF TEI Zeige Register ","fid":"copyLinkTextfield"}]},{"docId":"entry__1911-06-08","docUri":"entry__1911-06-08.html","score":1,"contexts":[{"form":"FFD","weight":"1","pos":55,"context":"....net\/21.11115\/0000-000B-<mark>FFD<\/mark>7-4 Faksimile PDF TEI Zeige Register ","fid":"copyLinkTextfield"}]},{"docId":"entry__1911-06-04","docUri":"entry__1911-06-04.html","score":1,"contexts":[{"form":"FFD","weight":"1","pos":125,"context":"....net\/21.11115\/0000-000B-<mark>FFD<\/mark>3-8 Faksimile PDF TEI Zeige Register ","fid":"copyLinkTextfield"}]},{"docId":"entry__1911-06-07","docUri":"entry__1911-06-07.html","score":1,"contexts":[{"form":"FFD","weight":"1","pos":61,"context":"....net\/21.11115\/0000-000B-<mark>FFD<\/mark>6-5 Faksimile PDF TEI Zeige Register ","fid":"copyLinkTextfield"}]},{"docId":"entry__1911-06-02","docUri":"entry__1911-06-02.html","score":1,"contexts":[{"form":"FFD","weight":"1","pos":46,"context":"....net\/21.11115\/0000-000B-<mark>FFD<\/mark>1-A Faksimile PDF TEI Zeige Register ","fid":"copyLinkTextfield"}]},{"docId":"entry__1911-06-09","docUri":"entry__1911-06-09.html","score":1,"contexts":[{"form":"FFD","weight":"1","pos":125,"context":"....net\/21.11115\/0000-000B-<mark>FFD<\/mark>8-3 Faksimile PDF TEI Zeige Register ","fid":"copyLinkTextfield"}]},{"docId":"entry__1922-10-06","docUri":"entry__1922-10-06.html","score":1,"contexts":[{"form":"FFD","weight":"1","pos":39,"context":"....net\/21.11115\/0000-000C-0<mark>FFD<\/mark>-8 Faksimile PDF TEI Zeige Register ","fid":"copyLinkTextfield"}]},{"docId":"entry__1911-06-05","docUri":"entry__1911-06-05.html","score":1,"contexts":[{"form":"FFD","weight":"1","pos":54,"context":"....net\/21.11115\/0000-000B-<mark>FFD<\/mark>4-7 Faksimile PDF TEI Zeige Register ","fid":"copyLinkTextfield"}]},{"docId":"entry__1911-06-06","docUri":"entry__1911-06-06.html","score":1,"contexts":[{"form":"FFD","weight":"1","pos":85,"context":"....net\/21.11115\/0000-000B-<mark>FFD<\/mark>5-6 Faksimile PDF TEI Zeige Register ","fid":"copyLinkTextfield"}]},{"docId":"entry__1911-06-10","docUri":"entry__1911-06-10.html","score":1,"contexts":[{"form":"FFD","weight":"1","pos":49,"context":"....net\/21.11115\/0000-000B-<mark>FFD<\/mark>9-2 Faksimile PDF TEI Zeige Register ","fid":"copyLinkTextfield"}]},{"docId":"entry__1911-06-01","docUri":"entry__1911-06-01.html","score":1,"contexts":[{"form":"FFD","weight":"1","pos":38,"context":"....net\/21.11115\/0000-000B-<mark>FFD<\/mark>0-B Faksimile PDF TEI Zeige Register ","fid":"copyLinkTextfield"}]}]}