{"stem":"gutmann-gels","instances":[{"docId":"entry__1904-05-07","docUri":"entry__1904-05-07.html","score":2,"contexts":[{"form":"Gutmann-Gelse’s","weight":"1","pos":11,"context":"...(Statue).― Lunch im Grd. Hotel mit <mark>Gutmann-Gelse’s<\/mark>.― Gepackt, gelesen.― Umberto genachtm.―","fid":"p__5"},{"form":"Gutmann-Gelse","weight":"1","pos":50,"context":" <mark>Gutmann-Gelse<\/mark> Arthur von ","fid":"nav-profile"}]},{"docId":"entry__1915-12-18","docUri":"entry__1915-12-18.html","score":2,"contexts":[{"form":"Gutmann-Gelse","weight":"1","pos":55,"context":" <mark>Gutmann-Gelse<\/mark> Albertine von ","fid":"nav-profile"},{"form":"Gutmann-Gelse","weight":"1","pos":59,"context":" <mark>Gutmann-Gelse<\/mark> Edmund von ","fid":"nav-profile"}]},{"docId":"entry__1922-05-19","docUri":"entry__1922-05-19.html","score":2,"contexts":[{"form":"Gutmann-Gelse","weight":"1","pos":16,"context":"...Briefe, Telegramme.― Blumen von Bar. Albertine <mark>Gutmann-Gelse<\/mark>,― Edith Beschi, Dir. Weiss (Nachbar);...","fid":"p__26"},{"form":"Gutmann-Gelse","weight":"1","pos":97,"context":" <mark>Gutmann-Gelse<\/mark> Albertine von ","fid":"nav-profile"}]},{"docId":"entry__1905-03-01","docUri":"entry__1905-03-01.html","score":2,"contexts":[{"form":"Gutmann-Gelses","weight":"1","pos":7,"context":"...Besorgungen.― Dictirt. (Roman.) ― Bei <mark>Gutmann-Gelses<\/mark>.―","fid":"p__4"},{"form":"Gutmann-Gelse","weight":"1","pos":58,"context":" <mark>Gutmann-Gelse<\/mark> Edmund von ","fid":"nav-profile"}]},{"docId":"entry__1904-05-06","docUri":"entry__1904-05-06.html","score":2,"contexts":[{"form":"Gutmann-Gelse","weight":"1","pos":28,"context":"...zurück ― Im Grd. Hotel Arth. v. <mark>Gutmann-Gelse<\/mark> und Frau.―","fid":"p__14"},{"form":"Gutmann-Gelse","weight":"1","pos":74,"context":" <mark>Gutmann-Gelse<\/mark> Arthur von ","fid":"nav-profile"}]},{"docId":"entry__1904-03-10","docUri":"entry__1904-03-10.html","score":2,"contexts":[{"form":"Gutmann-Gelse","weight":"1","pos":46,"context":" <mark>Gutmann-Gelse<\/mark> Albertine von ","fid":"nav-profile"},{"form":"Gutmann-Gelse","weight":"1","pos":50,"context":" <mark>Gutmann-Gelse<\/mark> Edmund von ","fid":"nav-profile"}]},{"docId":"entry__1895-07-10","docUri":"entry__1895-07-10.html","score":1,"contexts":[{"form":"Gutmann-Gelse","weight":"1","pos":66,"context":" <mark>Gutmann-Gelse<\/mark> Edmund von ","fid":"nav-profile"}]},{"docId":"entry__1899-06-28","docUri":"entry__1899-06-28.html","score":1,"contexts":[{"form":"Gutmann-Gelse","weight":"1","pos":41,"context":" <mark>Gutmann-Gelse<\/mark> Vilmos von ","fid":"nav-profile"}]},{"docId":"entry__1899-06-23","docUri":"entry__1899-06-23.html","score":1,"contexts":[{"form":"Gutmann-Gelse","weight":"1","pos":42,"context":" <mark>Gutmann-Gelse<\/mark> Edmund von ","fid":"nav-profile"}]},{"docId":"entry__1896-01-30","docUri":"entry__1896-01-30.html","score":1,"contexts":[{"form":"Gutmann-Gelse","weight":"1","pos":75,"context":" <mark>Gutmann-Gelse<\/mark> Albertine von ","fid":"nav-profile"}]},{"docId":"entry__1918-05-27","docUri":"entry__1918-05-27.html","score":1,"contexts":[{"form":"Gutmann-Gelse","weight":"1","pos":54,"context":" <mark>Gutmann-Gelse<\/mark> Albertine von ","fid":"nav-profile"}]},{"docId":"entry__1903-04-18","docUri":"entry__1903-04-18.html","score":1,"contexts":[{"form":"Gutmann-Gelse","weight":"1","pos":47,"context":" <mark>Gutmann-Gelse<\/mark> Edmund von ","fid":"nav-profile"}]},{"docId":"entry__1910-04-18","docUri":"entry__1910-04-18.html","score":1,"contexts":[{"form":"Gutmann-Gelse","weight":"1","pos":59,"context":" <mark>Gutmann-Gelse<\/mark> Albertine von ","fid":"nav-profile"}]},{"docId":"entry__1895-07-09","docUri":"entry__1895-07-09.html","score":1,"contexts":[{"form":"Gutmann-Gelse","weight":"1","pos":62,"context":" <mark>Gutmann-Gelse<\/mark> Edmund von ","fid":"nav-profile"}]},{"docId":"entry__1895-10-08","docUri":"entry__1895-10-08.html","score":1,"contexts":[{"form":"Gutmann-Gelse","weight":"1","pos":115,"context":" <mark>Gutmann-Gelse<\/mark> Edmund von ","fid":"nav-profile"}]},{"docId":"entry__1907-02-05","docUri":"entry__1907-02-05.html","score":1,"contexts":[{"form":"Gutmann-Gelse","weight":"1","pos":60,"context":" <mark>Gutmann-Gelse<\/mark> Albertine von ","fid":"nav-profile"}]},{"docId":"entry__1899-03-04","docUri":"entry__1899-03-04.html","score":1,"contexts":[{"form":"Gutmann-Gelse","weight":"1","pos":55,"context":" <mark>Gutmann-Gelse<\/mark> Edmund von ","fid":"nav-profile"}]},{"docId":"entry__1902-11-01","docUri":"entry__1902-11-01.html","score":1,"contexts":[{"form":"Gutmann-Gelse","weight":"1","pos":62,"context":" <mark>Gutmann-Gelse<\/mark> Edmund von ","fid":"nav-profile"}]},{"docId":"entry__1895-07-11","docUri":"entry__1895-07-11.html","score":1,"contexts":[{"form":"Gutmann-Gelse","weight":"1","pos":45,"context":" <mark>Gutmann-Gelse<\/mark> Edmund von ","fid":"nav-profile"}]},{"docId":"entry__1903-07-17","docUri":"entry__1903-07-17.html","score":1,"contexts":[{"form":"Gutmann-Gelse","weight":"1","pos":73,"context":" <mark>Gutmann-Gelse<\/mark> Edmund von ","fid":"nav-profile"}]},{"docId":"entry__1895-12-28","docUri":"entry__1895-12-28.html","score":1,"contexts":[{"form":"Gutmann-Gelse","weight":"1","pos":85,"context":" <mark>Gutmann-Gelse<\/mark> Edmund von ","fid":"nav-profile"}]},{"docId":"entry__1919-03-09","docUri":"entry__1919-03-09.html","score":1,"contexts":[{"form":"Gutmann-Gelse","weight":"1","pos":63,"context":" <mark>Gutmann-Gelse<\/mark> Ladislaus von ","fid":"nav-profile"}]},{"docId":"entry__1888-02-13","docUri":"entry__1888-02-13.html","score":1,"contexts":[{"form":"Gutmann-Gelse","weight":"1","pos":40,"context":" <mark>Gutmann-Gelse<\/mark> Edmund von ","fid":"nav-profile"}]},{"docId":"entry__1904-03-12","docUri":"entry__1904-03-12.html","score":1,"contexts":[{"form":"Gutmann-Gelse","weight":"1","pos":39,"context":" <mark>Gutmann-Gelse<\/mark> Edmund von ","fid":"nav-profile"}]},{"docId":"entry__1905-04-04","docUri":"entry__1905-04-04.html","score":1,"contexts":[{"form":"Gutmann-Gelse","weight":"1","pos":95,"context":" <mark>Gutmann-Gelse<\/mark> Edmund von ","fid":"nav-profile"}]},{"docId":"entry__1915-03-04","docUri":"entry__1915-03-04.html","score":1,"contexts":[{"form":"Gutmann-Gelse","weight":"1","pos":84,"context":" <mark>Gutmann-Gelse<\/mark> Albertine von ","fid":"nav-profile"}]},{"docId":"entry__1902-05-15","docUri":"entry__1902-05-15.html","score":1,"contexts":[{"form":"Gutmann-Gelse","weight":"1","pos":67,"context":" <mark>Gutmann-Gelse<\/mark> Albertine von ","fid":"nav-profile"}]},{"docId":"entry__1909-02-02","docUri":"entry__1909-02-02.html","score":1,"contexts":[{"form":"Gutmann-Gelse","weight":"1","pos":83,"context":" <mark>Gutmann-Gelse<\/mark> Edmund von ","fid":"nav-profile"}]}]}