{"stem":"inédit","instances":[{"docId":"entry__1921-03-18","docUri":"entry__1921-03-18.html","score":1,"contexts":[{"form":"inédits","weight":"1","pos":205,"context":"...Le drame de Varennes juin 1791 d'après des documents <mark>inédits<\/mark> et les relations des témoins oculaires","fid":"nav-contact"}]},{"docId":"entry__1921-03-11","docUri":"entry__1921-03-11.html","score":1,"contexts":[{"form":"inédits","weight":"1","pos":188,"context":"...Le drame de Varennes juin 1791 d'après des documents <mark>inédits<\/mark> et les relations des témoins oculaires","fid":"nav-contact"}]},{"docId":"entry__1917-11-03","docUri":"entry__1917-11-03.html","score":1,"contexts":[{"form":"inédits","weight":"1","pos":58,"context":"Mémoires <mark>inédits<\/mark> de Lamartine 1790-1815","fid":"nav-contact"}]},{"docId":"entry__1917-10-27","docUri":"entry__1917-10-27.html","score":1,"contexts":[{"form":"inédits","weight":"1","pos":130,"context":"Mémoires <mark>inédits<\/mark> de Lamartine 1790-1815","fid":"nav-contact"}]},{"docId":"entry__1921-03-07","docUri":"entry__1921-03-07.html","score":1,"contexts":[{"form":"inédits","weight":"1","pos":110,"context":"...Le drame de Varennes juin 1791 d'après des documents <mark>inédits<\/mark> et les relations des témoins oculaires","fid":"nav-contact"}]}]}