{"stem":"kalmár-kövesházi","instances":[{"docId":"entry__1908-12-20","docUri":"entry__1908-12-20.html","score":1,"contexts":[{"form":"Kalmár-Kövesházi","weight":"1","pos":47,"context":" <mark>Kalmár-Kövesházi<\/mark> Elsa von ","fid":"nav-profile"}]},{"docId":"entry__1911-11-18","docUri":"entry__1911-11-18.html","score":1,"contexts":[{"form":"Kalmár-Kövesházi","weight":"1","pos":68,"context":" <mark>Kalmár-Kövesházi<\/mark> Elsa von ","fid":"nav-profile"}]},{"docId":"entry__1904-02-22","docUri":"entry__1904-02-22.html","score":1,"contexts":[{"form":"Kalmár-Kövesházi","weight":"1","pos":54,"context":" <mark>Kalmár-Kövesházi<\/mark> Elsa von ","fid":"nav-profile"}]},{"docId":"entry__1913-05-11","docUri":"entry__1913-05-11.html","score":1,"contexts":[{"form":"Kalmár-Kövesházi","weight":"1","pos":50,"context":" <mark>Kalmár-Kövesházi<\/mark> Elsa von ","fid":"nav-profile"}]},{"docId":"entry__1913-09-29","docUri":"entry__1913-09-29.html","score":1,"contexts":[{"form":"Kalmár-Kövesházi","weight":"1","pos":32,"context":" <mark>Kalmár-Kövesházi<\/mark> Elsa von ","fid":"nav-profile"}]},{"docId":"entry__1911-11-20","docUri":"entry__1911-11-20.html","score":1,"contexts":[{"form":"Kalmár-Kövesházi","weight":"1","pos":36,"context":" <mark>Kalmár-Kövesházi<\/mark> Elsa von ","fid":"nav-profile"}]}]}