{"stem":"linda","instances":[{"docId":"entry__1886-04-12","docUri":"entry__1886-04-12.html","score":2,"contexts":[{"form":"Linda","weight":"1","pos":41,"context":"...Auch Frau Fbg., Emmy Ben., <mark>Linda<\/mark> H., und Rosa St.l. sind zu erwähnen....","fid":"p__25"},{"form":"Linda","weight":"1","pos":147,"context":" H. <mark>Linda<\/mark> ","fid":"nav-profile"}]},{"docId":"entry__1908-03-30","docUri":"entry__1908-03-30.html","score":1,"contexts":[{"form":"Linda","weight":"1","pos":65,"context":" Lützow <mark>Linda<\/mark> von ","fid":"nav-profile"}]},{"docId":"entry__1906-02-01","docUri":"entry__1906-02-01.html","score":1,"contexts":[{"form":"Linda","weight":"1","pos":59,"context":" Lützow <mark>Linda<\/mark> von ","fid":"nav-profile"}]}]}