{"stem":"multatuli-brief","instances":[{"docId":"entry__1908-01-12","docUri":"entry__1908-01-12.html","score":1,"contexts":[{"form":"Multatuli-Briefe","weight":"1","pos":297,"context":"<mark>Multatuli-Briefe<\/mark>","fid":"nav-contact"}]},{"docId":"entry__1907-11-30","docUri":"entry__1907-11-30.html","score":1,"contexts":[{"form":"Multatuli-Briefe","weight":"1","pos":79,"context":"<mark>Multatuli-Briefe<\/mark>","fid":"nav-contact"}]},{"docId":"entry__1907-11-28","docUri":"entry__1907-11-28.html","score":1,"contexts":[{"form":"Multatuli-Briefe","weight":"1","pos":79,"context":"<mark>Multatuli-Briefe<\/mark>","fid":"nav-contact"}]}]}