{"stem":"porada","instances":[{"docId":"entry__1920-10-24","docUri":"entry__1920-10-24.html","score":1,"contexts":[{"form":"Porada","weight":"1","pos":186,"context":" Rapoport-<mark>Porada<\/mark> Käthe von ","fid":"nav-profile"}]},{"docId":"entry__1921-01-09","docUri":"entry__1921-01-09.html","score":1,"contexts":[{"form":"Porada","weight":"1","pos":239,"context":" Rapoport-<mark>Porada<\/mark> Käthe von ","fid":"nav-profile"}]},{"docId":"entry__1920-03-09","docUri":"entry__1920-03-09.html","score":1,"contexts":[{"form":"Porada","weight":"1","pos":81,"context":" Rapoport-<mark>Porada<\/mark> Alfred von ","fid":"nav-profile"}]}]}