{"stem":"preußen","instances":[{"docId":"entry__1910-09-24","docUri":"entry__1910-09-24.html","score":2,"contexts":[{"form":"Preußen","weight":"1","pos":45,"context":"...andre, gegenübersteht. Der Gegensatz zwischen Polen und <mark>Preußen<\/mark> erscheint als der dichterischen Behandlung werth;― dies ungeheuer...","fid":"p__22"},{"form":"Preußen","weight":"1","pos":141,"context":"<mark>Preußen<\/mark>","fid":"nav-home"}]},{"docId":"entry__1917-04-26","docUri":"entry__1917-04-26.html","score":2,"contexts":[{"form":"Preußen","weight":"1","pos":44,"context":"...gegen Hohenzollern. Sympathie für Oesterreich, Antipathie gegen <mark>Preußen<\/mark>.― Unruhs neues Drama „Geschlecht“, revolutionär ―...","fid":"p__21"},{"form":"Preußen","weight":"1","pos":142,"context":"<mark>Preußen<\/mark>","fid":"nav-home"}]},{"docId":"entry__1914-02-25","docUri":"entry__1914-02-25.html","score":2,"contexts":[{"form":"Preußen","weight":"1","pos":103,"context":" Wilhelm II. von <mark>Preußen<\/mark> ","fid":"nav-profile"},{"form":"Preußen","weight":"1","pos":113,"context":"Louis Ferdinand, Prinz von <mark>Preußen<\/mark>","fid":"nav-contact"}]},{"docId":"entry__1916-03-06","docUri":"entry__1916-03-06.html","score":2,"contexts":[{"form":"Preußen","weight":"1","pos":17,"context":"...Bayern. Dort materiell und proviantiell besser als in <mark>Preußen<\/mark> und bei uns ― „Man will nicht mehr“ ―...","fid":"p__8"},{"form":"Preußen","weight":"1","pos":104,"context":"<mark>Preußen<\/mark>","fid":"nav-home"}]},{"docId":"entry__1928-11-30","docUri":"entry__1928-11-30.html","score":1,"contexts":[{"form":"Preußen","weight":"1","pos":111,"context":" Wilhelm II. von <mark>Preußen<\/mark> ","fid":"nav-profile"}]},{"docId":"entry__1918-10-26","docUri":"entry__1918-10-26.html","score":1,"contexts":[{"form":"Preußen","weight":"1","pos":83,"context":" Wilhelm II. von <mark>Preußen<\/mark> ","fid":"nav-profile"}]},{"docId":"entry__1914-12-31","docUri":"entry__1914-12-31.html","score":1,"contexts":[{"form":"Preußen","weight":"1","pos":272,"context":" Wilhelm II. von <mark>Preußen<\/mark> ","fid":"nav-profile"}]},{"docId":"entry__1918-11-10","docUri":"entry__1918-11-10.html","score":1,"contexts":[{"form":"Preußen","weight":"1","pos":112,"context":" Wilhelm II. von <mark>Preußen<\/mark> ","fid":"nav-profile"}]},{"docId":"entry__1926-02-15","docUri":"entry__1926-02-15.html","score":1,"contexts":[{"form":"Preußen","weight":"1","pos":87,"context":" Wilhelm II. von <mark>Preußen<\/mark> ","fid":"nav-profile"}]},{"docId":"entry__1913-10-29","docUri":"entry__1913-10-29.html","score":1,"contexts":[{"form":"Preußen","weight":"1","pos":137,"context":"Louis Ferdinand, Prinz von <mark>Preußen<\/mark>","fid":"nav-contact"}]},{"docId":"entry__1919-09-28","docUri":"entry__1919-09-28.html","score":1,"contexts":[{"form":"Preußen","weight":"1","pos":115,"context":"Louis Ferdinand, Prinz von <mark>Preußen<\/mark>","fid":"nav-contact"}]},{"docId":"entry__1924-01-22","docUri":"entry__1924-01-22.html","score":1,"contexts":[{"form":"Preußen","weight":"1","pos":94,"context":"<mark>Preußen<\/mark>","fid":"nav-home"}]},{"docId":"entry__1922-12-16","docUri":"entry__1922-12-16.html","score":1,"contexts":[{"form":"Preußen","weight":"1","pos":406,"context":"Louis Ferdinand, Prinz von <mark>Preußen<\/mark>","fid":"nav-contact"}]},{"docId":"entry__1916-03-22","docUri":"entry__1916-03-22.html","score":1,"contexts":[{"form":"Preußen","weight":"1","pos":63,"context":" Wilhelm II. von <mark>Preußen<\/mark> ","fid":"nav-profile"}]},{"docId":"entry__1914-01-08","docUri":"entry__1914-01-08.html","score":1,"contexts":[{"form":"Preußen","weight":"1","pos":122,"context":"Louis Ferdinand, Prinz von <mark>Preußen<\/mark>","fid":"nav-contact"}]},{"docId":"entry__1915-03-23","docUri":"entry__1915-03-23.html","score":1,"contexts":[{"form":"Preußen","weight":"1","pos":102,"context":" Wilhelm II. von <mark>Preußen<\/mark> ","fid":"nav-profile"}]},{"docId":"entry__1917-06-26","docUri":"entry__1917-06-26.html","score":1,"contexts":[{"form":"Preußen","weight":"1","pos":161,"context":" Wilhelm II. von <mark>Preußen<\/mark> ","fid":"nav-profile"}]},{"docId":"entry__1917-07-06","docUri":"entry__1917-07-06.html","score":1,"contexts":[{"form":"Preußen","weight":"1","pos":230,"context":" Wilhelm II. von <mark>Preußen<\/mark> ","fid":"nav-profile"}]},{"docId":"entry__1923-03-12","docUri":"entry__1923-03-12.html","score":1,"contexts":[{"form":"Preußen","weight":"1","pos":104,"context":" Wilhelm II. von <mark>Preußen<\/mark> ","fid":"nav-profile"}]},{"docId":"entry__1922-12-15","docUri":"entry__1922-12-15.html","score":1,"contexts":[{"form":"Preußen","weight":"1","pos":99,"context":"Louis Ferdinand, Prinz von <mark>Preußen<\/mark>","fid":"nav-contact"}]},{"docId":"entry__1916-01-27","docUri":"entry__1916-01-27.html","score":1,"contexts":[{"form":"Preußen","weight":"1","pos":154,"context":" Wilhelm II. von <mark>Preußen<\/mark> ","fid":"nav-profile"}]},{"docId":"entry__1913-12-13","docUri":"entry__1913-12-13.html","score":1,"contexts":[{"form":"Preußen","weight":"1","pos":83,"context":"Louis Ferdinand, Prinz von <mark>Preußen<\/mark>","fid":"nav-contact"}]},{"docId":"entry__1916-10-22","docUri":"entry__1916-10-22.html","score":1,"contexts":[{"form":"Preußen","weight":"1","pos":134,"context":" Wilhelm II. von <mark>Preußen<\/mark> ","fid":"nav-profile"}]},{"docId":"entry__1914-04-25","docUri":"entry__1914-04-25.html","score":1,"contexts":[{"form":"Preußen","weight":"1","pos":108,"context":" Wilhelm II. von <mark>Preußen<\/mark> ","fid":"nav-profile"}]},{"docId":"entry__1915-02-25","docUri":"entry__1915-02-25.html","score":1,"contexts":[{"form":"Preußen","weight":"1","pos":93,"context":" Wilhelm II. von <mark>Preußen<\/mark> ","fid":"nav-profile"}]},{"docId":"entry__1920-02-27","docUri":"entry__1920-02-27.html","score":1,"contexts":[{"form":"Preußen","weight":"1","pos":151,"context":" Wilhelm II. von <mark>Preußen<\/mark> ","fid":"nav-profile"}]},{"docId":"entry__1892-01-24","docUri":"entry__1892-01-24.html","score":1,"contexts":[{"form":"Preußen","weight":"1","pos":97,"context":" Wilhelm II. von <mark>Preußen<\/mark> ","fid":"nav-profile"}]},{"docId":"entry__1917-08-01","docUri":"entry__1917-08-01.html","score":1,"contexts":[{"form":"Preußen","weight":"1","pos":105,"context":" Wilhelm II. von <mark>Preußen<\/mark> ","fid":"nav-profile"}]},{"docId":"entry__1915-03-29","docUri":"entry__1915-03-29.html","score":1,"contexts":[{"form":"Preußen","weight":"1","pos":80,"context":" Wilhelm II. von <mark>Preußen<\/mark> ","fid":"nav-profile"}]},{"docId":"entry__1908-11-21","docUri":"entry__1908-11-21.html","score":1,"contexts":[{"form":"Preußen","weight":"1","pos":105,"context":" Wilhelm II. von <mark>Preußen<\/mark> ","fid":"nav-profile"}]},{"docId":"entry__1917-06-01","docUri":"entry__1917-06-01.html","score":1,"contexts":[{"form":"Preußen","weight":"1","pos":178,"context":" Wilhelm II. von <mark>Preußen<\/mark> ","fid":"nav-profile"}]},{"docId":"entry__1913-11-26","docUri":"entry__1913-11-26.html","score":1,"contexts":[{"form":"Preußen","weight":"1","pos":147,"context":"Louis Ferdinand, Prinz von <mark>Preußen<\/mark>","fid":"nav-contact"}]},{"docId":"entry__1927-07-12","docUri":"entry__1927-07-12.html","score":1,"contexts":[{"form":"Preußen","weight":"1","pos":120,"context":" Wilhelm II. von <mark>Preußen<\/mark> ","fid":"nav-profile"}]},{"docId":"entry__1915-01-13","docUri":"entry__1915-01-13.html","score":1,"contexts":[{"form":"Preußen","weight":"1","pos":54,"context":" Wilhelm II. von <mark>Preußen<\/mark> ","fid":"nav-profile"}]},{"docId":"entry__1917-04-17","docUri":"entry__1917-04-17.html","score":1,"contexts":[{"form":"Preußen","weight":"1","pos":168,"context":" Wilhelm II. von <mark>Preußen<\/mark> ","fid":"nav-profile"}]},{"docId":"entry__1914-09-13","docUri":"entry__1914-09-13.html","score":1,"contexts":[{"form":"Preußen","weight":"1","pos":215,"context":"<mark>Preußen<\/mark>","fid":"nav-home"}]},{"docId":"entry__1900-03-26","docUri":"entry__1900-03-26.html","score":1,"contexts":[{"form":"Preußen","weight":"1","pos":70,"context":" Wilhelm II. von <mark>Preußen<\/mark> ","fid":"nav-profile"}]},{"docId":"entry__1896-07-12","docUri":"entry__1896-07-12.html","score":1,"contexts":[{"form":"Preußen","weight":"1","pos":75,"context":" Wilhelm II. von <mark>Preußen<\/mark> ","fid":"nav-profile"}]},{"docId":"entry__1918-11-05","docUri":"entry__1918-11-05.html","score":1,"contexts":[{"form":"Preußen","weight":"1","pos":117,"context":" Wilhelm II. von <mark>Preußen<\/mark> ","fid":"nav-profile"}]},{"docId":"entry__1916-05-01","docUri":"entry__1916-05-01.html","score":1,"contexts":[{"form":"Preußen","weight":"1","pos":99,"context":"...Bd.― Grillparzer Fragmente durchgesehn.― Memoiren der Prinzessin von <mark>Preußen<\/mark>.― Segur weiter;― u. a.―","fid":"p__18"}]},{"docId":"entry__1919-12-10","docUri":"entry__1919-12-10.html","score":1,"contexts":[{"form":"Preußen","weight":"1","pos":105,"context":" Wilhelm II. von <mark>Preußen<\/mark> ","fid":"nav-profile"}]},{"docId":"entry__1917-02-15","docUri":"entry__1917-02-15.html","score":1,"contexts":[{"form":"Preußen","weight":"1","pos":96,"context":" Wilhelm II. von <mark>Preußen<\/mark> ","fid":"nav-profile"}]},{"docId":"entry__1918-12-27","docUri":"entry__1918-12-27.html","score":1,"contexts":[{"form":"Preußen","weight":"1","pos":218,"context":" Wilhelm II. von <mark>Preußen<\/mark> ","fid":"nav-profile"}]},{"docId":"entry__1919-10-26","docUri":"entry__1919-10-26.html","score":1,"contexts":[{"form":"Preußen","weight":"1","pos":153,"context":"Louis Ferdinand, Prinz von <mark>Preußen<\/mark>","fid":"nav-contact"}]},{"docId":"entry__1894-09-08","docUri":"entry__1894-09-08.html","score":1,"contexts":[{"form":"Preußen","weight":"1","pos":108,"context":" Wilhelm II. von <mark>Preußen<\/mark> ","fid":"nav-profile"}]},{"docId":"entry__1920-08-01","docUri":"entry__1920-08-01.html","score":1,"contexts":[{"form":"Preußen","weight":"1","pos":90,"context":"Louis Ferdinand, Prinz von <mark>Preußen<\/mark>","fid":"nav-contact"}]},{"docId":"entry__1920-02-05","docUri":"entry__1920-02-05.html","score":1,"contexts":[{"form":"Preußen","weight":"1","pos":154,"context":" Wilhelm II. von <mark>Preußen<\/mark> ","fid":"nav-profile"}]},{"docId":"entry__1918-11-09","docUri":"entry__1918-11-09.html","score":1,"contexts":[{"form":"Preußen","weight":"1","pos":128,"context":" Wilhelm II. von <mark>Preußen<\/mark> ","fid":"nav-profile"}]},{"docId":"entry__1909-09-01","docUri":"entry__1909-09-01.html","score":1,"contexts":[{"form":"Preußen","weight":"1","pos":130,"context":" Wilhelm II. von <mark>Preußen<\/mark> ","fid":"nav-profile"}]},{"docId":"entry__1903-07-03","docUri":"entry__1903-07-03.html","score":1,"contexts":[{"form":"Preußen","weight":"1","pos":98,"context":" Wilhelm II. von <mark>Preußen<\/mark> ","fid":"nav-profile"}]},{"docId":"entry__1916-10-21","docUri":"entry__1916-10-21.html","score":1,"contexts":[{"form":"Preußen","weight":"1","pos":153,"context":" Wilhelm II. von <mark>Preußen<\/mark> ","fid":"nav-profile"}]},{"docId":"entry__1921-06-07","docUri":"entry__1921-06-07.html","score":1,"contexts":[{"form":"Preußen","weight":"1","pos":142,"context":"Prinz Louis Ferdinand von <mark>Preußen<\/mark>","fid":"nav-contact"}]},{"docId":"entry__1914-01-09","docUri":"entry__1914-01-09.html","score":1,"contexts":[{"form":"Preußen","weight":"1","pos":111,"context":"Louis Ferdinand, Prinz von <mark>Preußen<\/mark>","fid":"nav-contact"}]}]}