{"stem":"romain","instances":[{"docId":"entry__1923-09-14","docUri":"entry__1923-09-14.html","score":2,"contexts":[{"form":"Romaine","weight":"1","pos":18,"context":".... Arlberg. Lese den schwachen Roman von Régnier <mark>Romaine<\/mark> Mirmault.","fid":"p__9"},{"form":"Romaine","weight":"1","pos":60,"context":"<mark>Romaine<\/mark> Mirmault","fid":"nav-contact"}]},{"docId":"entry__1914-11-07","docUri":"entry__1914-11-07.html","score":2,"contexts":[{"form":"Romain","weight":"1","pos":16,"context":"...ein etwas vager Plan; ob ich etwa zu <mark>Romain<\/mark> Rolland Verbindungen habe etc.―","fid":"p__7"},{"form":"Romain","weight":"1","pos":54,"context":" Rolland <mark>Romain<\/mark> ","fid":"nav-profile"}]},{"docId":"entry__1927-02-02","docUri":"entry__1927-02-02.html","score":2,"contexts":[{"form":"Romains","weight":"1","pos":6,"context":"2\/2 Vm. Generalprobe Dictator von <mark>Romains<\/mark>; das Stück regte mich (soweit ich es hörte...","fid":"p__11"},{"form":"Romains","weight":"1","pos":85,"context":" <mark>Romains<\/mark> Jules ","fid":"nav-profile"}]},{"docId":"entry__1918-05-11","docUri":"entry__1918-05-11.html","score":2,"contexts":[{"form":"Romain","weight":"1","pos":11,"context":"...die Papiernot, geistiges Eigentum, mangelndes Rechtsbewußtsein, <mark>Romain<\/mark> Rolland und vieles andre.","fid":"p__6"},{"form":"Romain","weight":"1","pos":119,"context":" Rolland <mark>Romain<\/mark> ","fid":"nav-profile"}]},{"docId":"entry__1926-05-16","docUri":"entry__1926-05-16.html","score":2,"contexts":[{"form":"Romains","weight":"1","pos":37,"context":"...Wien Auernheimer und Trebitsch. Flüchtig kennen gelernt Jules <mark>Romains<\/mark>.― Bekannte aus Holland, Daenemark.― Hans Jacob...","fid":"p__19"},{"form":"Romains","weight":"1","pos":124,"context":" <mark>Romains<\/mark> Jules ","fid":"nav-profile"}]},{"docId":"entry__1923-08-03","docUri":"entry__1923-08-03.html","score":2,"contexts":[{"form":"Romain","weight":"1","pos":21,"context":"...Auf der Terrasse Stefan Zweig und Frau; und <mark>Romain<\/mark> Rolland, um dessentwillen ich hier Aufenthalt nehm....","fid":"p__10"},{"form":"Romain","weight":"1","pos":84,"context":" Rolland <mark>Romain<\/mark> ","fid":"nav-profile"}]},{"docId":"entry__1919-11-27","docUri":"entry__1919-11-27.html","score":2,"contexts":[{"form":"Romain","weight":"1","pos":36,"context":".... Loewy brachte folgende Nachricht: Concordia wollte einen <mark>Romain<\/mark> Rolland Abend machen;― die hiesige französ. Mission erklärte...","fid":"p__11"},{"form":"Romain","weight":"1","pos":176,"context":" Rolland <mark>Romain<\/mark> ","fid":"nav-profile"}]},{"docId":"entry__1922-07-30","docUri":"entry__1922-07-30.html","score":2,"contexts":[{"form":"Romain","weight":"1","pos":129,"context":"...Ch. erzählt von seiner Haft in Genf, von <mark>Romain<\/mark> Rolland, der sich seine Briefe in fragwürdiger Weise...","fid":"p__13"},{"form":"Romain","weight":"1","pos":341,"context":" Rolland <mark>Romain<\/mark> ","fid":"nav-profile"}]},{"docId":"entry__1923-08-04","docUri":"entry__1923-08-04.html","score":1,"contexts":[{"form":"Romain","weight":"1","pos":102,"context":" Rolland <mark>Romain<\/mark> ","fid":"nav-profile"}]},{"docId":"entry__1915-01-17","docUri":"entry__1915-01-17.html","score":1,"contexts":[{"form":"Romain","weight":"1","pos":105,"context":" Rolland <mark>Romain<\/mark> ","fid":"nav-profile"}]},{"docId":"entry__1916-03-12","docUri":"entry__1916-03-12.html","score":1,"contexts":[{"form":"Romain","weight":"1","pos":78,"context":" Rolland <mark>Romain<\/mark> ","fid":"nav-profile"}]},{"docId":"entry__1921-01-04","docUri":"entry__1921-01-04.html","score":1,"contexts":[{"form":"Romain","weight":"1","pos":114,"context":" Rolland <mark>Romain<\/mark> ","fid":"nav-profile"}]},{"docId":"entry__1916-03-22","docUri":"entry__1916-03-22.html","score":1,"contexts":[{"form":"Romain","weight":"1","pos":56,"context":" Rolland <mark>Romain<\/mark> ","fid":"nav-profile"}]},{"docId":"entry__1921-04-17","docUri":"entry__1921-04-17.html","score":1,"contexts":[{"form":"Romain","weight":"1","pos":167,"context":" Rolland <mark>Romain<\/mark> ","fid":"nav-profile"}]},{"docId":"entry__1914-12-24","docUri":"entry__1914-12-24.html","score":1,"contexts":[{"form":"Romain","weight":"1","pos":158,"context":" Rolland <mark>Romain<\/mark> ","fid":"nav-profile"}]},{"docId":"entry__1928-07-22","docUri":"entry__1928-07-22.html","score":1,"contexts":[{"form":"Romain","weight":"1","pos":139,"context":" Rolland <mark>Romain<\/mark> ","fid":"nav-profile"}]},{"docId":"entry__1916-03-30","docUri":"entry__1916-03-30.html","score":1,"contexts":[{"form":"Romain","weight":"1","pos":84,"context":" Rolland <mark>Romain<\/mark> ","fid":"nav-profile"}]},{"docId":"entry__1919-04-22","docUri":"entry__1919-04-22.html","score":1,"contexts":[{"form":"Romain","weight":"1","pos":97,"context":" Rolland <mark>Romain<\/mark> ","fid":"nav-profile"}]},{"docId":"entry__1929-05-28","docUri":"entry__1929-05-28.html","score":1,"contexts":[{"form":"Romain","weight":"1","pos":101,"context":" Rolland <mark>Romain<\/mark> ","fid":"nav-profile"}]},{"docId":"entry__1925-01-13","docUri":"entry__1925-01-13.html","score":1,"contexts":[{"form":"Romain","weight":"1","pos":132,"context":" Rolland <mark>Romain<\/mark> ","fid":"nav-profile"}]},{"docId":"entry__1920-12-31","docUri":"entry__1920-12-31.html","score":1,"contexts":[{"form":"Romain","weight":"1","pos":175,"context":"<mark>Romain<\/mark> Rolland","fid":"nav-contact"}]},{"docId":"entry__1917-01-16","docUri":"entry__1917-01-16.html","score":1,"contexts":[{"form":"Romain","weight":"1","pos":69,"context":" Rolland <mark>Romain<\/mark> ","fid":"nav-profile"}]},{"docId":"entry__1916-04-23","docUri":"entry__1916-04-23.html","score":1,"contexts":[{"form":"Romain","weight":"1","pos":87,"context":" Rolland <mark>Romain<\/mark> ","fid":"nav-profile"}]},{"docId":"entry__1915-03-29","docUri":"entry__1915-03-29.html","score":1,"contexts":[{"form":"Romain","weight":"1","pos":74,"context":" Rolland <mark>Romain<\/mark> ","fid":"nav-profile"}]},{"docId":"entry__1916-03-10","docUri":"entry__1916-03-10.html","score":1,"contexts":[{"form":"Romain","weight":"1","pos":132,"context":" Rolland <mark>Romain<\/mark> ","fid":"nav-profile"}]},{"docId":"entry__1916-08-16","docUri":"entry__1916-08-16.html","score":1,"contexts":[{"form":"Romain","weight":"1","pos":67,"context":" Rolland <mark>Romain<\/mark> ","fid":"nav-profile"}]},{"docId":"entry__1916-03-11","docUri":"entry__1916-03-11.html","score":1,"contexts":[{"form":"Romain","weight":"1","pos":42,"context":" Rolland <mark>Romain<\/mark> ","fid":"nav-profile"}]},{"docId":"entry__1920-01-22","docUri":"entry__1920-01-22.html","score":1,"contexts":[{"form":"Romain","weight":"1","pos":103,"context":" Rolland <mark>Romain<\/mark> ","fid":"nav-profile"}]},{"docId":"entry__1925-07-19","docUri":"entry__1925-07-19.html","score":1,"contexts":[{"form":"Romain","weight":"1","pos":90,"context":"Liber amicorum <mark>Romain<\/mark> Rolland","fid":"nav-contact"}]},{"docId":"entry__1923-05-13","docUri":"entry__1923-05-13.html","score":1,"contexts":[{"form":"Romain","weight":"1","pos":109,"context":" Rolland <mark>Romain<\/mark> ","fid":"nav-profile"}]},{"docId":"entry__1924-05-13","docUri":"entry__1924-05-13.html","score":1,"contexts":[{"form":"Romain","weight":"1","pos":131,"context":" Rolland <mark>Romain<\/mark> ","fid":"nav-profile"}]},{"docId":"entry__1919-12-10","docUri":"entry__1919-12-10.html","score":1,"contexts":[{"form":"Romain","weight":"1","pos":99,"context":" Rolland <mark>Romain<\/mark> ","fid":"nav-profile"}]},{"docId":"entry__1925-07-14","docUri":"entry__1925-07-14.html","score":1,"contexts":[{"form":"Romain","weight":"1","pos":92,"context":"Liber amicorum <mark>Romain<\/mark> Rolland","fid":"nav-contact"}]},{"docId":"entry__1910-10-18","docUri":"entry__1910-10-18.html","score":1,"contexts":[{"form":"Romain","weight":"1","pos":56,"context":" Rolland <mark>Romain<\/mark> ","fid":"nav-profile"}]},{"docId":"entry__1926-08-20","docUri":"entry__1926-08-20.html","score":1,"contexts":[{"form":"Romain","weight":"1","pos":97,"context":" Rolland <mark>Romain<\/mark> ","fid":"nav-profile"}]},{"docId":"entry__1919-04-28","docUri":"entry__1919-04-28.html","score":1,"contexts":[{"form":"Romain","weight":"1","pos":76,"context":" Coolus <mark>Romain<\/mark> ","fid":"nav-profile"}]},{"docId":"entry__1925-08-05","docUri":"entry__1925-08-05.html","score":1,"contexts":[{"form":"Romain","weight":"1","pos":67,"context":"Liber amicorum <mark>Romain<\/mark> Rolland","fid":"nav-contact"}]}]}