{"stem":"währingerstraß","instances":[{"docId":"entry__1923-09-01","docUri":"entry__1923-09-01.html","score":2,"contexts":[{"form":"Währingerstraße","weight":"1","pos":22,"context":"...grade so weit von Frankgasse, wie jene Häuserreihe <mark>Währingerstraße<\/mark>, die immer in meinen Träumen wiederkehrt) ―...","fid":"p__29"},{"form":"Währingerstraße","weight":"1","pos":222,"context":"<mark>Währingerstraße<\/mark>","fid":"nav-home"}]},{"docId":"entry__1895-01-23","docUri":"entry__1895-01-23.html","score":2,"contexts":[{"form":"Währingerstraße","weight":"1","pos":211,"context":"...gingen zusammen weg, in ein kleines Kaffeehaus in der <mark>Währingerstraße<\/mark>.","fid":"p__7"},{"form":"Währingerstraße","weight":"1","pos":312,"context":"<mark>Währingerstraße<\/mark>","fid":"nav-home"}]},{"docId":"entry__1914-01-10","docUri":"entry__1914-01-10.html","score":2,"contexts":[{"form":"Währingerstraße","weight":"1","pos":5,"context":"10\/1 Traum: <mark>Währingerstraße<\/mark>, Vicki, mit irgend jemandem, zu seiner Hinrichtung...","fid":"p__7"},{"form":"Währingerstraße","weight":"1","pos":105,"context":"<mark>Währingerstraße<\/mark>","fid":"nav-home"}]},{"docId":"entry__1900-11-02","docUri":"entry__1900-11-02.html","score":1,"contexts":[{"form":"Währingerstraße","weight":"1","pos":58,"context":"<mark>Währingerstraße<\/mark>","fid":"nav-home"}]},{"docId":"entry__1915-12-11","docUri":"entry__1915-12-11.html","score":1,"contexts":[{"form":"Währingerstraße","weight":"1","pos":117,"context":"<mark>Währingerstraße<\/mark>","fid":"nav-home"}]},{"docId":"entry__1923-05-22","docUri":"entry__1923-05-22.html","score":1,"contexts":[{"form":"Währingerstraße","weight":"1","pos":101,"context":"<mark>Währingerstraße<\/mark>","fid":"nav-home"}]},{"docId":"entry__1923-02-22","docUri":"entry__1923-02-22.html","score":1,"contexts":[{"form":"Währingerstraße","weight":"1","pos":117,"context":"<mark>Währingerstraße<\/mark>","fid":"nav-home"}]},{"docId":"entry__1919-01-13","docUri":"entry__1919-01-13.html","score":1,"contexts":[{"form":"Währingerstraße","weight":"1","pos":116,"context":"<mark>Währingerstraße<\/mark>","fid":"nav-home"}]},{"docId":"entry__1923-04-02","docUri":"entry__1923-04-02.html","score":1,"contexts":[{"form":"Währingerstraße","weight":"1","pos":162,"context":"<mark>Währingerstraße<\/mark>","fid":"nav-home"}]},{"docId":"entry__1892-11-08","docUri":"entry__1892-11-08.html","score":1,"contexts":[{"form":"Währingerstraße","weight":"1","pos":69,"context":"<mark>Währingerstraße<\/mark>","fid":"nav-home"}]},{"docId":"entry__1918-12-09","docUri":"entry__1918-12-09.html","score":1,"contexts":[{"form":"Währingerstraße","weight":"1","pos":146,"context":"<mark>Währingerstraße<\/mark>","fid":"nav-home"}]}]}